evochi/v1/__init__.py
evochi/v1/evochi_pb2.py
evochi/v1/evochi_pb2.pyi
evochi/v1/evochi_pb2_grpc.py
evochi/v1/worker.py
evochi-0.1.4.dist-info/METADATA
evochi-0.1.4.dist-info/WHEEL
evochi-0.1.4.dist-info/top_level.txt
evochi-0.1.4.dist-info/RECORD
