Metadata-Version: 2.4
Name: evochi
Version: 0.1.4
Summary: The client implementation for the Evochi project.
Requires-Python: >=3.12
Requires-Dist: grpcio
Requires-Dist: grpcio-tools
Requires-Dist: zstandard
